README.rst
setup.py
nose_printlog.egg-info/PKG-INFO
nose_printlog.egg-info/SOURCES.txt
nose_printlog.egg-info/dependency_links.txt
nose_printlog.egg-info/entry_points.txt
nose_printlog.egg-info/not-zip-safe
nose_printlog.egg-info/requires.txt
nose_printlog.egg-info/top_level.txt
noseprintlog/__init__.py
noseprintlog/noseprintlog.py