Metadata-Version: 1.1
Name: nose-printlog
Version: 0.1.1
Summary: Print log to console in nose tests
Home-page: http://github.com/fbessho/nose-printlog/
Author: Fumihiro Bessho
Author-email: fumihiro.bessho@gmail.com
License: BSD
Platform: UNKNOWN
Classifier: Development Status :: 3 - Alpha
Classifier: Intended Audience :: Developers
Classifier: License :: OSI Approved :: BSD License
Classifier: Operating System :: OS Independent
Classifier: Programming Language :: Python
Classifier: Programming Language :: Python :: 2
Classifier: Programming Language :: Python :: 2.7
Classifier: Topic :: Software Development :: Libraries :: Python Modules
